cavl/__init__.py
cavl/_utils.py
cavl/automata.py
cavl/neighborhoods.py
cavl/rules.py
cavl/visualization.py
cavl-0.4.1.dist-info/LICENSE
cavl-0.4.1.dist-info/METADATA
cavl-0.4.1.dist-info/WHEEL
cavl-0.4.1.dist-info/top_level.txt
cavl-0.4.1.dist-info/RECORD
