Metadata-Version: 2.1
Name: cavl
Version: 0.4.1
Summary: A simple library for visualizing cellular automata
Home-page: https://github.com/jstnd/cavl
Author: Justin Doornbos
Author-email: jstndevel@gmail.com
License: MIT
Platform: UNKNOWN
Classifier: Development Status :: 3 - Alpha
Classifier: Intended Audience :: Developers
Classifier: Programming Language :: Python :: 3.7
Classifier: License :: OSI Approved :: MIT License
Requires-Python: >=3.7
License-File: LICENSE
Requires-Dist: matplotlib (>=3.4.3)
Requires-Dist: numpy (>=1.21.2)
